env_manager/__init__.py
env_manager/main.py
solugen.env_manager-0.1.0.dist-info/METADATA
solugen.env_manager-0.1.0.dist-info/WHEEL
solugen.env_manager-0.1.0.dist-info/top_level.txt
solugen.env_manager-0.1.0.dist-info/RECORD
