Metadata-Version: 2.1
Name: solugen.env-manager
Version: 0.1.0
Summary: A Python library to manage environment variables
Home-page: https://bitbucket.org/solugenai/env-manager
Author: Elad Laor
Author-email: elad.l@solugen.ai
License: MIT
Classifier: Programming Language :: Python :: 3
Requires-Python: >=3.6
Requires-Dist: python-dotenv==1.0.1
